{
  "ngDeps": {
    "1": "angular2.src.core.debug.debug_element",
    "3": [
      {
        "1": "package:angular2/src/facade/lang.dart",
        "2": [
          "Type",
          "isPresent",
          "isBlank"
        ],
        "5": false
      },
      {
        "1": "package:angular2/src/facade/collection.dart",
        "2": [
          "ListWrapper",
          "MapWrapper",
          "Predicate"
        ],
        "5": false
      },
      {
        "1": "package:angular2/src/facade/exceptions.dart",
        "2": [
          "unimplemented"
        ],
        "5": false
      },
      {
        "1": "package:angular2/src/core/linker/element.dart",
        "2": [
          "AppElement"
        ],
        "5": false
      },
      {
        "1": "package:angular2/src/core/linker/view.dart",
        "2": [
          "AppView"
        ],
        "5": false
      },
      {
        "1": "package:angular2/src/core/linker/element_ref.dart",
        "2": [
          "ElementRef",
          "ElementRef_"
        ],
        "5": false
      }
    ],
    "6": "debug_element.dart"
  }
}